{
  "_fv": 33,
  "_type": "structure",
  "definition": {
    "structure": "exitdeadssss",
    "randomlyRotateStructure": false,
    "surfaceDetectionType": "First motion blocking block",
    "spawnProbability": 34500,
    "minCountPerChunk": 1,
    "maxCountPerChunk": 1,
    "spawnLocation": "Underground",
    "spawnHeightOffset": 2,
    "spawnXOffset": 0,
    "spawnZOffset": 0,
    "spawnWorldTypes": [
      "CUSTOM:DeathDIM"
    ],
    "restrictionBlocks": [],
    "restrictionBiomes": [
      {
        "value": "CUSTOM:DeadWoodsBIOME"
      }
    ],
    "ignoreBlocks": "STRUCTURE_BLOCK",
    "generateCondition": {
      "name": "TestOleg"
    }
  }
}